LICENSE.TXT
README.md
pyproject.toml
setup.py
dema/__init__.py
dema/concepts_desc.csv
dema/database.py
dema/engine.py
dema.egg-info/PKG-INFO
dema.egg-info/SOURCES.txt
dema.egg-info/dependency_links.txt
dema.egg-info/requires.txt
dema.egg-info/top_level.txt
dema/back/__init__.py
dema/back/descriptor.py
dema/back/exception.py
dema/back/utils_io.py
dema/back/utils_sql.py
dema/back/utils_view.py
dema/front/__init__.py
dema/front/app.py
dema/front/logger.py
dema/front/style.css
dema/front/waiter.py
dema/front/manager/__init__.py
dema/front/manager/base.py
dema/front/manager/concept.py
dema/front/manager/superset.py
dema/utils/__init__.py
dema/utils/utils_misc.py