Metadata-Version: 2.1
Name: dema
Version: 0.2.5
Summary: Data Engine MAnagment tool for python
Home-page: https://github.com/gab23r/dema
Author: Gabriel Robin
Classifier: Programming Language :: Python :: 3
Classifier: License :: OSI Approved :: MIT License
Classifier: Operating System :: OS Independent
Requires-Python: >=3.11
Provides-Extra: front
License-File: LICENSE.TXT
